README.md
setup.py
zetanize/__init__.py
zetanize/zetanize.py
zetanize.egg-info/PKG-INFO
zetanize.egg-info/SOURCES.txt
zetanize.egg-info/dependency_links.txt
zetanize.egg-info/top_level.txt